prompt_guardrails/__init__.py
prompt_guardrails-0.1.0.dist-info/licenses/LICENSE
tests/__init__.py
prompt_guardrails-0.1.0.dist-info/METADATA
prompt_guardrails-0.1.0.dist-info/WHEEL
prompt_guardrails-0.1.0.dist-info/top_level.txt
prompt_guardrails-0.1.0.dist-info/RECORD
